alibabacloud_paielasticdatasetaccelerator20220801/__init__.py
alibabacloud_paielasticdatasetaccelerator20220801/client.py
alibabacloud_paielasticdatasetaccelerator20220801/models/__init__.py
alibabacloud_paielasticdatasetaccelerator20220801/models/_bind_endpoint_response.py
alibabacloud_paielasticdatasetaccelerator20220801/models/_bind_endpoint_response_body.py
alibabacloud_paielasticdatasetaccelerator20220801/models/_create_endpoint_request.py
alibabacloud_paielasticdatasetaccelerator20220801/models/_create_endpoint_response.py
alibabacloud_paielasticdatasetaccelerator20220801/models/_create_endpoint_response_body.py
alibabacloud_paielasticdatasetaccelerator20220801/models/_create_instance_request.py
alibabacloud_paielasticdatasetaccelerator20220801/models/_create_instance_response.py
alibabacloud_paielasticdatasetaccelerator20220801/models/_create_instance_response_body.py
alibabacloud_paielasticdatasetaccelerator20220801/models/_create_slot_request.py
alibabacloud_paielasticdatasetaccelerator20220801/models/_create_slot_response.py
alibabacloud_paielasticdatasetaccelerator20220801/models/_create_slot_response_body.py
alibabacloud_paielasticdatasetaccelerator20220801/models/_create_slots_request.py
alibabacloud_paielasticdatasetaccelerator20220801/models/_create_slots_response.py
alibabacloud_paielasticdatasetaccelerator20220801/models/_create_slots_response_body.py
alibabacloud_paielasticdatasetaccelerator20220801/models/_create_tag_request.py
alibabacloud_paielasticdatasetaccelerator20220801/models/_create_tag_response.py
alibabacloud_paielasticdatasetaccelerator20220801/models/_create_tag_response_body.py
alibabacloud_paielasticdatasetaccelerator20220801/models/_delete_endpoint_response.py
alibabacloud_paielasticdatasetaccelerator20220801/models/_delete_endpoint_response_body.py
alibabacloud_paielasticdatasetaccelerator20220801/models/_delete_instance_response.py
alibabacloud_paielasticdatasetaccelerator20220801/models/_delete_instance_response_body.py
alibabacloud_paielasticdatasetaccelerator20220801-1.1.3.dist-info/LICENSE
alibabacloud_paielasticdatasetaccelerator20220801-1.1.3.dist-info/METADATA
alibabacloud_paielasticdatasetaccelerator20220801-1.1.3.dist-info/WHEEL
alibabacloud_paielasticdatasetaccelerator20220801-1.1.3.dist-info/top_level.txt
alibabacloud_paielasticdatasetaccelerator20220801-1.1.3.dist-info/RECORD
