Metadata-Version: 2.1
Name: alibabacloud-paielasticdatasetaccelerator20220801
Version: 1.1.3
Summary: Alibaba Cloud PAIElasticDatasetAccelerator (20220801) SDK Library for Python
Home-page: https://github.com/aliyun/alibabacloud-python-sdk
Author: Alibaba Cloud SDK
Author-email: sdk-team@alibabacloud.com
License: Apache License 2.0
Keywords: alibabacloud,paielasticdatasetaccelerator20220801
Platform: any
Classifier: Development Status :: 4 - Beta
Classifier: Intended Audience :: Developers
Classifier: License :: OSI Approved :: Apache Software License
Classifier: Programming Language :: Python
Classifier: Programming Language :: Python :: 3
Classifier: Programming Language :: Python :: 3.7
Classifier: Programming Language :: Python :: 3.8
Classifier: Programming Language :: Python :: 3.9
Classifier: Programming Language :: Python :: 3.10
Classifier: Programming Language :: Python :: 3.11
Classifier: Programming Language :: Python :: 3.12
Classifier: Topic :: Software Development
Requires-Python: >=3.7
License-File: LICENSE
Requires-Dist: alibabacloud-tea-openapi (<1.0.0,>=0.4.1)
Requires-Dist: darabonba-core (<2.0.0,>=1.0.0)
